AUTHORS.rst
CONTRIBUTING.rst
HISTORY.rst
LICENSE
MANIFEST.in
README.rst
setup.cfg
setup.py
docs/Makefile
docs/authors.rst
docs/conf.py
docs/contributing.rst
docs/history.rst
docs/index.rst
docs/installation.rst
docs/make.bat
docs/readme.rst
docs/usage.rst
surfraw_pinboard.egg-info/PKG-INFO
surfraw_pinboard.egg-info/SOURCES.txt
surfraw_pinboard.egg-info/dependency_links.txt
surfraw_pinboard.egg-info/entry_points.txt
surfraw_pinboard.egg-info/not-zip-safe
surfraw_pinboard.egg-info/requires.txt
surfraw_pinboard.egg-info/top_level.txt
surfrawpinboard/__init__.py
surfrawpinboard/bookmarks.py
surfrawpinboard/cli.py