Metadata-Version: 1.1
Name: surfraw-pinboard
Version: 0.1.0
Summary: Python Boilerplate contains all the boilerplate you need to create a Python package.
Home-page: https://github.com/hypebeast/surfraw-pinboard
Author: Sebastian Ruml
Author-email: sebastian@sebastianruml.name
License: MIT license
Keywords: surfraw pinboard
Platform: UNKNOWN
Classifier: Development Status :: 2 - Pre-Alpha
Classifier: Intended Audience :: Developers
Classifier: License :: OSI Approved :: MIT License
Classifier: Natural Language :: English
Classifier: Programming Language :: Python :: 2
Classifier: Programming Language :: Python :: 2.6
Classifier: Programming Language :: Python :: 2.7
Classifier: Programming Language :: Python :: 3
Classifier: Programming Language :: Python :: 3.3
Classifier: Programming Language :: Python :: 3.4
Classifier: Programming Language :: Python :: 3.5
